ne21c.cpython-39-darwin.so
ymw16.cpython-39-darwin.so
pygedm/__init__.py
pygedm/gal01.inp
pygedm/healpix_utils.py
pygedm/ne2001_wrapper.py
pygedm/ne_arms_log_mod.inp
pygedm/ne_gc.inp
pygedm/neclumpN.NE2001.dat
pygedm/nelism.inp
pygedm/nevoidN.NE2001.dat
pygedm/pygedm.py
pygedm/spiral.txt
pygedm/ymw16_wrapper.py
pygedm/ymw16par.txt
pygedm/yt2020.py
pygedm-3.2.4.dist-info/METADATA
pygedm-3.2.4.dist-info/WHEEL
pygedm-3.2.4.dist-info/top_level.txt
pygedm-3.2.4.dist-info/RECORD
