Metadata-Version: 2.1
Name: pygedm
Version: 3.2.4
Summary: Python/C++ version of NE2001, YMW16, and YT2020 electron density models
Home-page: https://github.com/frbs/pygedm
Author: D. C. Price
Author-email: dancpr@berkeley.edu
License: UNKNOWN
Download-URL: https://github.com/telegraphic/pygedm/archive/3.2.4.tar.gz
Platform: UNKNOWN
Requires-Python: >=3.6
Requires-Dist: pybind11 (>=2.2)
Requires-Dist: astropy
